plot_tree/__init__.py
plot_tree/child_parent_example.csv
plot_tree/cli.py
plot_tree/common.py
plot_tree/default.py
plot_tree/example_csv.py
plot_tree/tree_plotter.py
treeplots-0.10.8.dist-info/METADATA
treeplots-0.10.8.dist-info/WHEEL
treeplots-0.10.8.dist-info/entry_points.txt
treeplots-0.10.8.dist-info/RECORD
