Metadata-Version: 2.4
Name: treeplots
Version: 0.10.8
Summary: CLI tool to create tree views from a csv file with child-parent relationships.
Author: cheny
Requires-Python: >=3.9.2,<4.0.0
Classifier: Programming Language :: Python :: 3
Classifier: Programming Language :: Python :: 3.10
Classifier: Programming Language :: Python :: 3.11
Classifier: Programming Language :: Python :: 3.12
Classifier: Programming Language :: Python :: 3.13
Classifier: Programming Language :: Python :: 3.14
Requires-Dist: anytree (>=2.13.0,<2.14.0)
Requires-Dist: pyyaml (>=6.0.1,<6.1.0)
Requires-Dist: typer (>=0.19.2,<1.0)
